[
  {
    "folder": "isp",
    "filename": "Samsung__A12__A127F.webp",
    "brand": "Samsung",
    "model": "A12",
    "code": "A127F",
    "keywords": [
      "a12",
      "a12 a127f",
      "samsung a12",
      "a127f",
      "samsung"
    ]
  },
  {
    "folder": "isp",
    "filename": "MT6789V.jpg",
    "brand": "MT6789V",
    "model": "",
    "code": "",
    "keywords": [
      "mt6789v ",
      " ",
      "mt6789v"
    ]
  },
  {
    "folder": "isp",
    "filename": "Vivo__Y29 5G__PD2421F.jpg",
    "brand": "Vivo",
    "model": "Y29 5G",
    "code": "PD2421F",
    "keywords": [
      "vivo",
      "y29 5g",
      "pd2421f",
      "vivo y29 5g",
      "y29 5g pd2421f"
    ]
  },
  {
    "folder": "isp",
    "filename": "Honor__X8d__ABR-LX1.jpg",
    "brand": "Honor",
    "model": "X8d",
    "code": "ABR-LX1",
    "keywords": [
      "honor x8d",
      "x8d",
      "honor",
      "abr-lx1",
      "x8d abr-lx1"
    ]
  },
  {
    "folder": "isp",
    "filename": "Huawei__NOVA 13.jpg",
    "brand": "Huawei",
    "model": "NOVA 13",
    "code": "",
    "keywords": [
      "nova 13",
      "huawei",
      "nova 13 ",
      "huawei nova 13"
    ]
  },
  {
    "folder": "isp",
    "filename": "Oppo__A5 4G__CPH2727.jpg",
    "brand": "Oppo",
    "model": "A5 4G",
    "code": "CPH2727",
    "keywords": [
      "a5 4g",
      "a5 4g cph2727",
      "oppo a5 4g",
      "cph2727",
      "oppo"
    ]
  },
  {
    "folder": "isp",
    "filename": "Oppo__A5 5G__CPH2693.jpg",
    "brand": "Oppo",
    "model": "A5 5G",
    "code": "CPH2693",
    "keywords": [
      "a5 5g cph2693",
      "cph2693",
      "oppo a5 5g",
      "a5 5g",
      "oppo"
    ]
  },
  {
    "folder": "isp",
    "filename": "Vivo__X200 FE__PD2465.jpg",
    "brand": "Vivo",
    "model": "X200 FE",
    "code": "PD2465",
    "keywords": [
      "vivo",
      "vivo x200 fe",
      "x200 fe",
      "pd2465",
      "x200 fe pd2465"
    ]
  },
  {
    "folder": "isp",
    "filename": "Vivo__Y36 4G__PD2280.jpg",
    "brand": "Vivo",
    "model": "Y36 4G",
    "code": "PD2280",
    "keywords": [
      "y36 4g pd2280",
      "vivo",
      "vivo y36 4g",
      "y36 4g",
      "pd2280"
    ]
  },
  {
    "folder": "isp",
    "filename": "Samsung__A06__A065F.jpg",
    "brand": "Samsung",
    "model": "A06",
    "code": "A065F",
    "keywords": [
      "samsung a06",
      "a06 a065f",
      "a065f",
      "a06",
      "samsung"
    ]
  },
  {
    "folder": "isp",
    "filename": "Samsung__S22 5G__S901N.jpg",
    "brand": "Samsung",
    "model": "S22 5G",
    "code": "S901N",
    "keywords": [
      "s22 5g",
      "s901n",
      "samsung s22 5g",
      "s22 5g s901n",
      "samsung"
    ]
  },
  {
    "folder": "isp",
    "filename": "Samsung__S24 Plus__S926U.jpg",
    "brand": "Samsung",
    "model": "S24 Plus",
    "code": "S926U",
    "keywords": [
      "s24 plus",
      "s926u",
      "samsung s24 plus",
      "s24 plus s926u",
      "samsung"
    ]
  },
  {
    "folder": "isp",
    "filename": "Honor__X9b__ALIN-NX1.jpg",
    "brand": "Honor",
    "model": "X9b",
    "code": "ALIN-NX1",
    "keywords": [
      "honor",
      "x9b",
      "honor x9b",
      "alin-nx1",
      "x9b alin-nx1"
    ]
  },
  {
    "folder": "isp",
    "filename": "Samsung__S26 Ultra__S946B.jpg",
    "brand": "Samsung",
    "model": "S26 Ultra",
    "code": "S946B",
    "keywords": [
      "s26 ultra",
      "s26 ultra s946b",
      "s946b",
      "samsung s26 ultra",
      "samsung"
    ]
  },
  {
    "folder": "isp",
    "filename": "a135f.jpg",
    "brand": "a135f",
    "model": "",
    "code": "",
    "keywords": [
      "a135f ",
      " ",
      "a135f"
    ]
  },
  {
    "folder": "isp",
    "filename": "Realme__15x 5G__RMX5250.jpg",
    "brand": "Realme",
    "model": "15x 5G",
    "code": "RMX5250",
    "keywords": [
      "15x 5g",
      "rmx5250",
      "15x 5g rmx5250",
      "realme",
      "realme 15x 5g"
    ]
  },
  {
    "folder": "rsa",
    "filename": "Redmi__Note 11__Spes&Spesn.jpg",
    "brand": "Redmi",
    "model": "Note 11",
    "code": "Spes&Spesn",
    "keywords": [
      "note 11",
      "redmi",
      "redmi note 11",
      "spes&spesn",
      "note 11 spes&spesn"
    ]
  },
  {
    "folder": "testpoint",
    "filename": "Redmi__Note 13 Pro 5G__Garnet.jpg",
    "brand": "Redmi",
    "model": "Note 13 Pro 5G",
    "code": "Garnet",
    "keywords": [
      "garnet",
      "note 13 pro 5g garnet",
      "redmi note 13 pro 5g",
      "redmi",
      "note 13 pro 5g"
    ]
  },
  {
    "folder": "testpoint",
    "filename": "Oppo__A78 5G__CPH2495.jpg",
    "brand": "Oppo",
    "model": "A78 5G",
    "code": "CPH2495",
    "keywords": [
      "a78 5g",
      "oppo a78 5g",
      "cph2495",
      "oppo",
      "a78 5g cph2495"
    ]
  },
  {
    "folder": "testpoint",
    "filename": "Vivo__Y300 Plus__PD2422F.jpg",
    "brand": "Vivo",
    "model": "Y300 Plus",
    "code": "PD2422F",
    "keywords": [
      "vivo",
      "pd2422f",
      "y300 plus",
      "y300 plus pd2422f",
      "vivo y300 plus"
    ]
  },
  {
    "folder": "testpoint",
    "filename": "Samsung__A54__A546B.jpg",
    "brand": "Samsung",
    "model": "A54",
    "code": "A546B",
    "keywords": [
      "a54",
      "a546b",
      "samsung a54",
      "samsung",
      "a54 a546b"
    ]
  },
  {
    "folder": "testpoint",
    "filename": "Samsung__A12__A125F.jpg",
    "brand": "Samsung",
    "model": "A12",
    "code": "A125F",
    "keywords": [
      "a12",
      "a12 a125f",
      "samsung a12",
      "a125f",
      "samsung"
    ]
  },
  {
    "folder": "testpoint",
    "filename": "Oppo__A57__CPH2387.jpg",
    "brand": "Oppo",
    "model": "A57",
    "code": "CPH2387",
    "keywords": [
      "cph2387",
      "oppo a57",
      "a57 cph2387",
      "a57",
      "oppo"
    ]
  },
  {
    "folder": "testpoint",
    "filename": "Samsung__A13__A135F.webp",
    "brand": "Samsung",
    "model": "A13",
    "code": "A135F",
    "keywords": [
      "samsung a13",
      "a13",
      "a13 a135f",
      "samsung",
      "a135f"
    ]
  },
  {
    "folder": "testpoint",
    "filename": "Samsung__A32__A325F.jpg",
    "brand": "Samsung",
    "model": "A32",
    "code": "A325F",
    "keywords": [
      "a325f",
      "a32 a325f",
      "samsung a32",
      "a32",
      "samsung"
    ]
  },
  {
    "folder": "testpoint",
    "filename": "Oppo__A77__CPH2385.jpg",
    "brand": "Oppo",
    "model": "A77",
    "code": "CPH2385",
    "keywords": [
      "a77",
      "oppo a77",
      "a77 cph2385",
      "cph2385",
      "oppo"
    ]
  },
  {
    "folder": "testpoint",
    "filename": "Motorola__Moto G04__XT2421.jpg",
    "brand": "Motorola",
    "model": "Moto G04",
    "code": "XT2421",
    "keywords": [
      "motorola moto g04",
      "moto g04 xt2421",
      "moto g04",
      "motorola",
      "xt2421"
    ]
  },
  {
    "folder": "testpoint",
    "filename": "Oppo__Reno8 T 4G__CPH2481.jpg",
    "brand": "Oppo",
    "model": "Reno8 T 4G",
    "code": "CPH2481",
    "keywords": [
      "reno8 t 4g",
      "cph2481",
      "reno8 t 4g cph2481",
      "oppo reno8 t 4g",
      "oppo"
    ]
  },
  {
    "folder": "testpoint",
    "filename": "Redmi__Note 10__Mojito.jpg",
    "brand": "Redmi",
    "model": "Note 10",
    "code": "Mojito",
    "keywords": [
      "note 10 mojito",
      "mojito",
      "redmi note 10",
      "redmi",
      "note 10"
    ]
  },
  {
    "folder": "testpoint",
    "filename": "Redmi__Note 8__Ginkgo.jpg",
    "brand": "Redmi",
    "model": "Note 8",
    "code": "Ginkgo",
    "keywords": [
      "note 8",
      "redmi",
      "ginkgo",
      "redmi note 8",
      "note 8 ginkgo"
    ]
  },
  {
    "folder": "testpoint",
    "filename": "Oppo__A54__CPH2239.jpg",
    "brand": "Oppo",
    "model": "A54",
    "code": "CPH2239",
    "keywords": [
      "a54",
      "a54 cph2239",
      "oppo a54",
      "oppo",
      "cph2239"
    ]
  }
]